microsoftvision/__init__.py
microsoftvision/models/__init__.py
microsoftvision/models/resnext.py
microsoftvision/models/utils.py
microsoftvision-1.0.5.dist-info/METADATA
microsoftvision-1.0.5.dist-info/WHEEL
microsoftvision-1.0.5.dist-info/top_level.txt
microsoftvision-1.0.5.dist-info/RECORD
