Metadata-Version: 2.1
Name: microsoftvision
Version: 1.0.5
Summary: Downloads pretrained Microsoft Vision models
Home-page: UNKNOWN
License: UNKNOWN
Platform: UNKNOWN
Requires-Dist: torch (>=1.2.0)
Requires-Dist: azure-storage-blob
Requires-Dist: azure-identity
Requires-Dist: tqdm
